{
    "walk": {
        "name": "armor.crystal_walk",
        "volumeMin": 50,
        "volumeMax": 50
    },
    "run": {
        "name": "armor.crystal_run",
        "volumeMin": 50,
        "volumeMax": 50
    },
    "wander": {
        "name": "armor.crystal_walk",
        "volumeMin": 50,
        "volumeMax": 50
    },
    "jump": {
        "name": "armor.crystal_walk",
        "volumeMin": 50,
        "volumeMax": 50
    },
    "land": [
        {
            "name": "armor.crystal_walk",
            "volumeMin": 50,
            "volumeMax": 50
        },
        {
            "name": "armor.crystal_walk",
            "volumeMin": 50,
            "volumeMax": 50
        },
        {
            "delay": 50,
            "name": "armor.crystal_run",
            "volumeMin": 50,
            "volumeMax": 50
        }
    ]
}
